senial1.vhd
library ieee;
use ieee.std_logic_1164.all;
use ieee.numeric_std.all;


entity senoidal is
    generic (
        BITS_DATO  : natural := 12;   -- Número de bits de cada dato-valor
        N_MUESTRAS : natural := 256   -- Cantidad de muestras por período de señal
    );
    port (
        clk      : in  std_logic;
        reset    : in  std_logic;
        enable   : in  std_logic;
        seno_o   : out std_logic_vector(BITS_DATO - 1 downto 0)
    );

    -- Esta función calcula la cantidad de bits necesarios 
    -- para almacenar un número entero positivo (distinto de cero)
    function log2ceil(n: positive) return natural is
        variable result: natural := 0;   -- Valor a devolver
        variable temp: positive := n;    -- Número máximo que debe almacenar
                                         -- (no puede ser cero)
      begin
        while temp > 1 loop
          result := result + 1;
          temp := temp / 2;
        end loop;
      
        if temp > 0 then
          result := result + 1;
        end if;
      
        return result;
    end function;

end entity senoidal;

architecture senoidal_arq of senoidal is
    type lut_type is array (0 to N_MUESTRAS - 1) of std_logic_vector(BITS_DATO - 1 downto 0);
    constant lut : lut_type := (
        "100000000000", "100000110010", "100001100100", "100010010110", "100011001000", "100011111010", "100100101100", "100101011110", "100110001111", "100111000000", 
        "100111110001", "101000100010", "101001010010", "101010000010", "101010110001", "101011100000", "101100001111", "101100111101", "101101101011", "101110011000", 
        "101111000101", "101111110001", "110000011100", "110001000111", "110001110001", "110010011010", "110011000011", "110011101011", "110100010010", "110100111001", 
        "110101011111", "110110000011", "110110100111", "110111001010", "110111101101", "111000001110", "111000101110", "111001001110", "111001101100", "111010001010", 
        "111010100110", "111011000001", "111011011100", "111011110101", "111100001101", "111100100100", "111100111010", "111101001111", "111101100011", "111101110110", 
        "111110000111", "111110011000", "111110100111", "111110110101", "111111000010", "111111001101", "111111011000", "111111100001", "111111101001", "111111110000", 
        "111111110101", "111111111001", "111111111101", "111111111110", "111111111111", "111111111110", "111111111101", "111111111001", "111111110101", "111111110000", 
        "111111101001", "111111100001", "111111011000", "111111001101", "111111000010", "111110110101", "111110100111", "111110011000", "111110000111", "111101110110", 
        "111101100011", "111101001111", "111100111010", "111100100100", "111100001101", "111011110101", "111011011100", "111011000001", "111010100110", "111010001010", 
        "111001101100", "111001001110", "111000101110", "111000001110", "110111101101", "110111001010", "110110100111", "110110000011", "110101011111", "110100111001", 
        "110100010010", "110011101011", "110011000011", "110010011010", "110001110001", "110001000111", "110000011100", "101111110001", "101111000101", "101110011000", 
        "101101101011", "101100111101", "101100001111", "101011100000", "101010110001", "101010000010", "101001010010", "101000100010", "100111110001", "100111000000", 
        "100110001111", "100101011110", "100100101100", "100011111010", "100011001000", "100010010110", "100001100100", "100000110010", "100000000000", "011111001101", 
        "011110011011", "011101101001", "011100110111", "011100000101", "011011010011", "011010100001", "011001110000", "011000111111", "011000001110", "010111011101", 
        "010110101101", "010101111101", "010101001110", "010100011111", "010011110000", "010011000010", "010010010100", "010001100111", "010000111010", "010000001110", 
        "001111100011", "001110111000", "001110001110", "001101100101", "001100111100", "001100010100", "001011101101", "001011000110", "001010100000", "001001111100", 
        "001001011000", "001000110101", "001000010010", "000111110001", "000111010001", "000110110001", "000110010011", "000101110101", "000101011001", "000100111110", 
        "000100100011", "000100001010", "000011110010", "000011011011", "000011000101", "000010110000", "000010011100", "000010001001", "000001111000", "000001100111", 
        "000001011000", "000001001010", "000000111101", "000000110010", "000000100111", "000000011110", "000000010110", "000000001111", "000000001010", "000000000110", 
        "000000000010", "000000000001", "000000000000", "000000000001", "000000000010", "000000000110", "000000001010", "000000001111", "000000010110", "000000011110", 
        "000000100111", "000000110010", "000000111101", "000001001010", "000001011000", "000001100111", "000001111000", "000010001001", "000010011100", "000010110000", 
        "000011000101", "000011011011", "000011110010", "000100001010", "000100100011", "000100111110", "000101011001", "000101110101", "000110010011", "000110110001", 
        "000111010001", "000111110001", "001000010010", "001000110101", "001001011000", "001001111100", "001010100000", "001011000110", "001011101101", "001100010100", 
        "001100111100", "001101100101", "001110001110", "001110111000", "001111100011", "010000001110", "010000111010", "010001100111", "010010010100", "010011000010", 
        "010011110000", "010100011111", "010101001110", "010101111101", "010110101101", "010111011101", "011000001110", "011000111111", "011001110000", "011010100001", 
        "011011010011", "011100000101", "011100110111", "011101101001", "011110011011", "011111001101"
     );

    signal lut_index : unsigned(log2ceil(N_MUESTRAS) - 1 downto 0);
    signal dato      : std_logic_vector(BITS_DATO - 1 downto 0);
    
begin
    process (clk, reset)
    begin
        if reset = '1' then
            lut_index <= (others => '0');
            dato      <= (others => '0');
        elsif rising_edge(clk) then
            if enable = '1' then
                lut_index <= lut_index + 1;
                if lut_index = N_MUESTRAS - 1 then
                    lut_index <= (others => '0');
                end if;
                dato <= lut(to_integer(lut_index));
            end if;
        end if;
    end process;

    seno_o <= dato;
end architecture senoidal_arq;

senial1_tb.vhd
library IEEE;
use IEEE.std_logic_1164.all;
use ieee.numeric_std.all;

entity senial1_tb is
end;

architecture senial1_tb_arq of senial1_tb is

    constant DW_tb:     natural := 12;
    signal clk_tb:      std_logic := '0';
    signal reset_tb:    std_logic := '1';
    signal enable_tb:   std_logic := '0';
    signal sine_out_tb: std_logic_vector(DW_tb - 1 downto 0);

begin

    clk_tb    <= not clk_tb after 5 ns;
    reset_tb  <= '0' after 50 ns;
    enable_tb <= '1' after 50 ns;
    
    DUT: entity work.senoidal
        generic map(
            BITS_DATO => DW_tb
        )
        port map(
            clk      =>  clk_tb,
            reset    =>  reset_tb,
            enable   =>  enable_tb,
            seno_o   =>  sine_out_tb
        );
end;

Simulacion/senial1_tb.vcd
$date
  Sat Jun 10 16:10:54 2023
$end
$version
  GHDL v0
$end
$timescale
  1 fs
$end
$scope module standard $end
$upscope $end
$scope module std_logic_1164 $end
$upscope $end
$scope module numeric_std $end
$upscope $end
$scope module senial1_tb $end
$var reg 1 ! clk_tb $end
$var reg 1 " reset_tb $end
$var reg 1 # enable_tb $end
$var reg 12 $ sine_out_tb[11:0] $end
$scope module dut $end
$var reg 1 % clk $end
$var reg 1 & reset $end
$var reg 1 ' enable $end
$var reg 12 ( seno_o[11:0] $end
$var reg 9 ) lut_index[8:0] $end
$var reg 12 * dato[11:0] $end
$upscope $end
$upscope $end
$enddefinitions $end
#0
0!
1"
0#
b000000000000 $
0%
1&
0'
b000000000000 (
b000000000 )
b000000000000 *
#5000000
1!
1%
#10000000
0!
0%
#15000000
1!
1%
#20000000
0!
0%
#25000000
1!
1%
#30000000
0!
0%
#35000000
1!
1%
#40000000
0!
0%
#45000000
1!
1%
#50000000
0!
0"
1#
0%
0&
1'
#55000000
1!
b100000000000 $
1%
b100000000000 (
b000000001 )
b100000000000 *
#60000000
0!
0%
#65000000
1!
b100000110010 $
1%
b100000110010 (
b000000010 )
b100000110010 *
#70000000
0!
0%
#75000000
1!
b100001100100 $
1%
b100001100100 (
b000000011 )
b100001100100 *
#80000000
0!
0%
#85000000
1!
b100010010110 $
1%
b100010010110 (
b000000100 )
b100010010110 *
#90000000
0!
0%
#95000000
1!
b100011001000 $
1%
b100011001000 (
b000000101 )
b100011001000 *
#100000000
0!
0%
#105000000
1!
b100011111010 $
1%
b100011111010 (
b000000110 )
b100011111010 *
#110000000
0!
0%
#115000000
1!
b100100101100 $
1%
b100100101100 (
b000000111 )
b100100101100 *
#120000000
0!
0%
#125000000
1!
b100101011110 $
1%
b100101011110 (
b000001000 )
b100101011110 *
#130000000
0!
0%
#135000000
1!
b100110001111 $
1%
b100110001111 (
b000001001 )
b100110001111 *
#140000000
0!
0%
#145000000
1!
b100111000000 $
1%
b100111000000 (
b000001010 )
b100111000000 *
#150000000
0!
0%
#155000000
1!
b100111110001 $
1%
b100111110001 (
b000001011 )
b100111110001 *
#160000000
0!
0%
#165000000
1!
b101000100010 $
1%
b101000100010 (
b000001100 )
b101000100010 *
#170000000
0!
0%
#175000000
1!
b101001010010 $
1%
b101001010010 (
b000001101 )
b101001010010 *
#180000000
0!
0%
#185000000
1!
b101010000010 $
1%
b101010000010 (
b000001110 )
b101010000010 *
#190000000
0!
0%
#195000000
1!
b101010110001 $
1%
b101010110001 (
b000001111 )
b101010110001 *
#200000000
0!
0%
#205000000
1!
b101011100000 $
1%
b101011100000 (
b000010000 )
b101011100000 *
#210000000
0!
0%
#215000000
1!
b101100001111 $
1%
b101100001111 (
b000010001 )
b101100001111 *
#220000000
0!
0%
#225000000
1!
b101100111101 $
1%
b101100111101 (
b000010010 )
b101100111101 *
#230000000
0!
0%
#235000000
1!
b101101101011 $
1%
b101101101011 (
b000010011 )
b101101101011 *
#240000000
0!
0%
#245000000
1!
b101110011000 $
1%
b101110011000 (
b000010100 )
b101110011000 *
#250000000
0!
0%
#255000000
1!
b101111000101 $
1%
b101111000101 (
b000010101 )
b101111000101 *
#260000000
0!
0%
#265000000
1!
b101111110001 $
1%
b101111110001 (
b000010110 )
b101111110001 *
#270000000
0!
0%
#275000000
1!
b110000011100 $
1%
b110000011100 (
b000010111 )
b110000011100 *
#280000000
0!
0%
#285000000
1!
b110001000111 $
1%
b110001000111 (
b000011000 )
b110001000111 *
#290000000
0!
0%
#295000000
1!
b110001110001 $
1%
b110001110001 (
b000011001 )
b110001110001 *
#300000000
0!
0%
#305000000
1!
b110010011010 $
1%
b110010011010 (
b000011010 )
b110010011010 *
#310000000
0!
0%
#315000000
1!
b110011000011 $
1%
b110011000011 (
b000011011 )
b110011000011 *
#320000000
0!
0%
#325000000
1!
b110011101011 $
1%
b110011101011 (
b000011100 )
b110011101011 *
#330000000
0!
0%
#335000000
1!
b110100010010 $
1%
b110100010010 (
b000011101 )
b110100010010 *
#340000000
0!
0%
#345000000
1!
b110100111001 $
1%
b110100111001 (
b000011110 )
b110100111001 *
#350000000
0!
0%
#355000000
1!
b110101011111 $
1%
b110101011111 (
b000011111 )
b110101011111 *
#360000000
0!
0%
#365000000
1!
b110110000011 $
1%
b110110000011 (
b000100000 )
b110110000011 *
#370000000
0!
0%
#375000000
1!
b110110100111 $
1%
b110110100111 (
b000100001 )
b110110100111 *
#380000000
0!
0%
#385000000
1!
b110111001010 $
1%
b110111001010 (
b000100010 )
b110111001010 *
#390000000
0!
0%
#395000000
1!
b110111101101 $
1%
b110111101101 (
b000100011 )
b110111101101 *
#400000000
0!
0%
#405000000
1!
b111000001110 $
1%
b111000001110 (
b000100100 )
b111000001110 *
#410000000
0!
0%
#415000000
1!
b111000101110 $
1%
b111000101110 (
b000100101 )
b111000101110 *
#420000000
0!
0%
#425000000
1!
b111001001110 $
1%
b111001001110 (
b000100110 )
b111001001110 *
#430000000
0!
0%
#435000000
1!
b111001101100 $
1%
b111001101100 (
b000100111 )
b111001101100 *
#440000000
0!
0%
#445000000
1!
b111010001010 $
1%
b111010001010 (
b000101000 )
b111010001010 *
#450000000
0!
0%
#455000000
1!
b111010100110 $
1%
b111010100110 (
b000101001 )
b111010100110 *
#460000000
0!
0%
#465000000
1!
b111011000001 $
1%
b111011000001 (
b000101010 )
b111011000001 *
#470000000
0!
0%
#475000000
1!
b111011011100 $
1%
b111011011100 (
b000101011 )
b111011011100 *
#480000000
0!
0%
#485000000
1!
b111011110101 $
1%
b111011110101 (
b000101100 )
b111011110101 *
#490000000
0!
0%
#495000000
1!
b111100001101 $
1%
b111100001101 (
b000101101 )
b111100001101 *
#500000000
0!
0%
#505000000
1!
b111100100100 $
1%
b111100100100 (
b000101110 )
b111100100100 *
#510000000
0!
0%
#515000000
1!
b111100111010 $
1%
b111100111010 (
b000101111 )
b111100111010 *
#520000000
0!
0%
#525000000
1!
b111101001111 $
1%
b111101001111 (
b000110000 )
b111101001111 *
#530000000
0!
0%
#535000000
1!
b111101100011 $
1%
b111101100011 (
b000110001 )
b111101100011 *
#540000000
0!
0%
#545000000
1!
b111101110110 $
1%
b111101110110 (
b000110010 )
b111101110110 *
#550000000
0!
0%
#555000000
1!
b111110000111 $
1%
b111110000111 (
b000110011 )
b111110000111 *
#560000000
0!
0%
#565000000
1!
b111110011000 $
1%
b111110011000 (
b000110100 )
b111110011000 *
#570000000
0!
0%
#575000000
1!
b111110100111 $
1%
b111110100111 (
b000110101 )
b111110100111 *
#580000000
0!
0%
#585000000
1!
b111110110101 $
1%
b111110110101 (
b000110110 )
b111110110101 *
#590000000
0!
0%
#595000000
1!
b111111000010 $
1%
b111111000010 (
b000110111 )
b111111000010 *
#600000000
0!
0%
#605000000
1!
b111111001101 $
1%
b111111001101 (
b000111000 )
b111111001101 *
#610000000
0!
0%
#615000000
1!
b111111011000 $
1%
b111111011000 (
b000111001 )
b111111011000 *
#620000000
0!
0%
#625000000
1!
b111111100001 $
1%
b111111100001 (
b000111010 )
b111111100001 *
#630000000
0!
0%
#635000000
1!
b111111101001 $
1%
b111111101001 (
b000111011 )
b111111101001 *
#640000000
0!
0%
#645000000
1!
b111111110000 $
1%
b111111110000 (
b000111100 )
b111111110000 *
#650000000
0!
0%
#655000000
1!
b111111110101 $
1%
b111111110101 (
b000111101 )
b111111110101 *
#660000000
0!
0%
#665000000
1!
b111111111001 $
1%
b111111111001 (
b000111110 )
b111111111001 *
#670000000
0!
0%
#675000000
1!
b111111111101 $
1%
b111111111101 (
b000111111 )
b111111111101 *
#680000000
0!
0%
#685000000
1!
b111111111110 $
1%
b111111111110 (
b001000000 )
b111111111110 *
#690000000
0!
0%
#695000000
1!
b111111111111 $
1%
b111111111111 (
b001000001 )
b111111111111 *
#700000000
0!
0%
#705000000
1!
b111111111110 $
1%
b111111111110 (
b001000010 )
b111111111110 *
#710000000
0!
0%
#715000000
1!
b111111111101 $
1%
b111111111101 (
b001000011 )
b111111111101 *
#720000000
0!
0%
#725000000
1!
b111111111001 $
1%
b111111111001 (
b001000100 )
b111111111001 *
#730000000
0!
0%
#735000000
1!
b111111110101 $
1%
b111111110101 (
b001000101 )
b111111110101 *
#740000000
0!
0%
#745000000
1!
b111111110000 $
1%
b111111110000 (
b001000110 )
b111111110000 *
#750000000
0!
0%
#755000000
1!
b111111101001 $
1%
b111111101001 (
b001000111 )
b111111101001 *
#760000000
0!
0%
#765000000
1!
b111111100001 $
1%
b111111100001 (
b001001000 )
b111111100001 *
#770000000
0!
0%
#775000000
1!
b111111011000 $
1%
b111111011000 (
b001001001 )
b111111011000 *
#780000000
0!
0%
#785000000
1!
b111111001101 $
1%
b111111001101 (
b001001010 )
b111111001101 *
#790000000
0!
0%
#795000000
1!
b111111000010 $
1%
b111111000010 (
b001001011 )
b111111000010 *
#800000000
0!
0%
#805000000
1!
b111110110101 $
1%
b111110110101 (
b001001100 )
b111110110101 *
#810000000
0!
0%
#815000000
1!
b111110100111 $
1%
b111110100111 (
b001001101 )
b111110100111 *
#820000000
0!
0%
#825000000
1!
b111110011000 $
1%
b111110011000 (
b001001110 )
b111110011000 *
#830000000
0!
0%
#835000000
1!
b111110000111 $
1%
b111110000111 (
b001001111 )
b111110000111 *
#840000000
0!
0%
#845000000
1!
b111101110110 $
1%
b111101110110 (
b001010000 )
b111101110110 *
#850000000
0!
0%
#855000000
1!
b111101100011 $
1%
b111101100011 (
b001010001 )
b111101100011 *
#860000000
0!
0%
#865000000
1!
b111101001111 $
1%
b111101001111 (
b001010010 )
b111101001111 *
#870000000
0!
0%
#875000000
1!
b111100111010 $
1%
b111100111010 (
b001010011 )
b111100111010 *
#880000000
0!
0%
#885000000
1!
b111100100100 $
1%
b111100100100 (
b001010100 )
b111100100100 *
#890000000
0!
0%
#895000000
1!
b111100001101 $
1%
b111100001101 (
b001010101 )
b111100001101 *
#900000000
0!
0%
#905000000
1!
b111011110101 $
1%
b111011110101 (
b001010110 )
b111011110101 *
#910000000
0!
0%
#915000000
1!
b111011011100 $
1%
b111011011100 (
b001010111 )
b111011011100 *
#920000000
0!
0%
#925000000
1!
b111011000001 $
1%
b111011000001 (
b001011000 )
b111011000001 *
#930000000
0!
0%
#935000000
1!
b111010100110 $
1%
b111010100110 (
b001011001 )
b111010100110 *
#940000000
0!
0%
#945000000
1!
b111010001010 $
1%
b111010001010 (
b001011010 )
b111010001010 *
#950000000
0!
0%
#955000000
1!
b111001101100 $
1%
b111001101100 (
b001011011 )
b111001101100 *
#960000000
0!
0%
#965000000
1!
b111001001110 $
1%
b111001001110 (
b001011100 )
b111001001110 *
#970000000
0!
0%
#975000000
1!
b111000101110 $
1%
b111000101110 (
b001011101 )
b111000101110 *
#980000000
0!
0%
#985000000
1!
b111000001110 $
1%
b111000001110 (
b001011110 )
b111000001110 *
#990000000
0!
0%
#995000000
1!
b110111101101 $
1%
b110111101101 (
b001011111 )
b110111101101 *
#1000000000
0!
0%
#1005000000
1!
b110111001010 $
1%
b110111001010 (
b001100000 )
b110111001010 *
#1010000000
0!
0%
#1015000000
1!
b110110100111 $
1%
b110110100111 (
b001100001 )
b110110100111 *
#1020000000
0!
0%
#1025000000
1!
b110110000011 $
1%
b110110000011 (
b001100010 )
b110110000011 *
#1030000000
0!
0%
#1035000000
1!
b110101011111 $
1%
b110101011111 (
b001100011 )
b110101011111 *
#1040000000
0!
0%
#1045000000
1!
b110100111001 $
1%
b110100111001 (
b001100100 )
b110100111001 *
#1050000000
0!
0%
#1055000000
1!
b110100010010 $
1%
b110100010010 (
b001100101 )
b110100010010 *
#1060000000
0!
0%
#1065000000
1!
b110011101011 $
1%
b110011101011 (
b001100110 )
b110011101011 *
#1070000000
0!
0%
#1075000000
1!
b110011000011 $
1%
b110011000011 (
b001100111 )
b110011000011 *
#1080000000
0!
0%
#1085000000
1!
b110010011010 $
1%
b110010011010 (
b001101000 )
b110010011010 *
#1090000000
0!
0%
#1095000000
1!
b110001110001 $
1%
b110001110001 (
b001101001 )
b110001110001 *
#1100000000
0!
0%
#1105000000
1!
b110001000111 $
1%
b110001000111 (
b001101010 )
b110001000111 *
#1110000000
0!
0%
#1115000000
1!
b110000011100 $
1%
b110000011100 (
b001101011 )
b110000011100 *
#1120000000
0!
0%
#1125000000
1!
b101111110001 $
1%
b101111110001 (
b001101100 )
b101111110001 *
#1130000000
0!
0%
#1135000000
1!
b101111000101 $
1%
b101111000101 (
b001101101 )
b101111000101 *
#1140000000
0!
0%
#1145000000
1!
b101110011000 $
1%
b101110011000 (
b001101110 )
b101110011000 *
#1150000000
0!
0%
#1155000000
1!
b101101101011 $
1%
b101101101011 (
b001101111 )
b101101101011 *
#1160000000
0!
0%
#1165000000
1!
b101100111101 $
1%
b101100111101 (
b001110000 )
b101100111101 *
#1170000000
0!
0%
#1175000000
1!
b101100001111 $
1%
b101100001111 (
b001110001 )
b101100001111 *
#1180000000
0!
0%
#1185000000
1!
b101011100000 $
1%
b101011100000 (
b001110010 )
b101011100000 *
#1190000000
0!
0%
#1195000000
1!
b101010110001 $
1%
b101010110001 (
b001110011 )
b101010110001 *
#1200000000
0!
0%
#1205000000
1!
b101010000010 $
1%
b101010000010 (
b001110100 )
b101010000010 *
#1210000000
0!
0%
#1215000000
1!
b101001010010 $
1%
b101001010010 (
b001110101 )
b101001010010 *
#1220000000
0!
0%
#1225000000
1!
b101000100010 $
1%
b101000100010 (
b001110110 )
b101000100010 *
#1230000000
0!
0%
#1235000000
1!
b100111110001 $
1%
b100111110001 (
b001110111 )
b100111110001 *
#1240000000
0!
0%
#1245000000
1!
b100111000000 $
1%
b100111000000 (
b001111000 )
b100111000000 *
#1250000000
0!
0%
#1255000000
1!
b100110001111 $
1%
b100110001111 (
b001111001 )
b100110001111 *
#1260000000
0!
0%
#1265000000
1!
b100101011110 $
1%
b100101011110 (
b001111010 )
b100101011110 *
#1270000000
0!
0%
#1275000000
1!
b100100101100 $
1%
b100100101100 (
b001111011 )
b100100101100 *
#1280000000
0!
0%
#1285000000
1!
b100011111010 $
1%
b100011111010 (
b001111100 )
b100011111010 *
#1290000000
0!
0%
#1295000000
1!
b100011001000 $
1%
b100011001000 (
b001111101 )
b100011001000 *
#1300000000
0!
0%
#1305000000
1!
b100010010110 $
1%
b100010010110 (
b001111110 )
b100010010110 *
#1310000000
0!
0%
#1315000000
1!
b100001100100 $
1%
b100001100100 (
b001111111 )
b100001100100 *
#1320000000
0!
0%
#1325000000
1!
b100000110010 $
1%
b100000110010 (
b010000000 )
b100000110010 *
#1330000000
0!
0%
#1335000000
1!
b100000000000 $
1%
b100000000000 (
b010000001 )
b100000000000 *
#1340000000
0!
0%
#1345000000
1!
b011111001101 $
1%
b011111001101 (
b010000010 )
b011111001101 *
#1350000000
0!
0%
#1355000000
1!
b011110011011 $
1%
b011110011011 (
b010000011 )
b011110011011 *
#1360000000
0!
0%
#1365000000
1!
b011101101001 $
1%
b011101101001 (
b010000100 )
b011101101001 *
#1370000000
0!
0%
#1375000000
1!
b011100110111 $
1%
b011100110111 (
b010000101 )
b011100110111 *
#1380000000
0!
0%
#1385000000
1!
b011100000101 $
1%
b011100000101 (
b010000110 )
b011100000101 *
#1390000000
0!
0%
#1395000000
1!
b011011010011 $
1%
b011011010011 (
b010000111 )
b011011010011 *
#1400000000
0!
0%
#1405000000
1!
b011010100001 $
1%
b011010100001 (
b010001000 )
b011010100001 *
#1410000000
0!
0%
#1415000000
1!
b011001110000 $
1%
b011001110000 (
b010001001 )
b011001110000 *
#1420000000
0!
0%
#1425000000
1!
b011000111111 $
1%
b011000111111 (
b010001010 )
b011000111111 *
#1430000000
0!
0%
#1435000000
1!
b011000001110 $
1%
b011000001110 (
b010001011 )
b011000001110 *
#1440000000
0!
0%
#1445000000
1!
b010111011101 $
1%
b010111011101 (
b010001100 )
b010111011101 *
#1450000000
0!
0%
#1455000000
1!
b010110101101 $
1%
b010110101101 (
b010001101 )
b010110101101 *
#1460000000
0!
0%
#1465000000
1!
b010101111101 $
1%
b010101111101 (
b010001110 )
b010101111101 *
#1470000000
0!
0%
#1475000000
1!
b010101001110 $
1%
b010101001110 (
b010001111 )
b010101001110 *
#1480000000
0!
0%
#1485000000
1!
b010100011111 $
1%
b010100011111 (
b010010000 )
b010100011111 *
#1490000000
0!
0%
#1495000000
1!
b010011110000 $
1%
b010011110000 (
b010010001 )
b010011110000 *
#1500000000
0!
0%
#1505000000
1!
b010011000010 $
1%
b010011000010 (
b010010010 )
b010011000010 *
#1510000000
0!
0%
#1515000000
1!
b010010010100 $
1%
b010010010100 (
b010010011 )
b010010010100 *
#1520000000
0!
0%
#1525000000
1!
b010001100111 $
1%
b010001100111 (
b010010100 )
b010001100111 *
#1530000000
0!
0%
#1535000000
1!
b010000111010 $
1%
b010000111010 (
b010010101 )
b010000111010 *
#1540000000
0!
0%
#1545000000
1!
b010000001110 $
1%
b010000001110 (
b010010110 )
b010000001110 *
#1550000000
0!
0%
#1555000000
1!
b001111100011 $
1%
b001111100011 (
b010010111 )
b001111100011 *
#1560000000
0!
0%
#1565000000
1!
b001110111000 $
1%
b001110111000 (
b010011000 )
b001110111000 *
#1570000000
0!
0%
#1575000000
1!
b001110001110 $
1%
b001110001110 (
b010011001 )
b001110001110 *
#1580000000
0!
0%
#1585000000
1!
b001101100101 $
1%
b001101100101 (
b010011010 )
b001101100101 *
#1590000000
0!
0%
#1595000000
1!
b001100111100 $
1%
b001100111100 (
b010011011 )
b001100111100 *
#1600000000
0!
0%
#1605000000
1!
b001100010100 $
1%
b001100010100 (
b010011100 )
b001100010100 *
#1610000000
0!
0%
#1615000000
1!
b001011101101 $
1%
b001011101101 (
b010011101 )
b001011101101 *
#1620000000
0!
0%
#1625000000
1!
b001011000110 $
1%
b001011000110 (
b010011110 )
b001011000110 *
#1630000000
0!
0%
#1635000000
1!
b001010100000 $
1%
b001010100000 (
b010011111 )
b001010100000 *
#1640000000
0!
0%
#1645000000
1!
b001001111100 $
1%
b001001111100 (
b010100000 )
b001001111100 *
#1650000000
0!
0%
#1655000000
1!
b001001011000 $
1%
b001001011000 (
b010100001 )
b001001011000 *
#1660000000
0!
0%
#1665000000
1!
b001000110101 $
1%
b001000110101 (
b010100010 )
b001000110101 *
#1670000000
0!
0%
#1675000000
1!
b001000010010 $
1%
b001000010010 (
b010100011 )
b001000010010 *
#1680000000
0!
0%
#1685000000
1!
b000111110001 $
1%
b000111110001 (
b010100100 )
b000111110001 *
#1690000000
0!
0%
#1695000000
1!
b000111010001 $
1%
b000111010001 (
b010100101 )
b000111010001 *
#1700000000
0!
0%
#1705000000
1!
b000110110001 $
1%
b000110110001 (
b010100110 )
b000110110001 *
#1710000000
0!
0%
#1715000000
1!
b000110010011 $
1%
b000110010011 (
b010100111 )
b000110010011 *
#1720000000
0!
0%
#1725000000
1!
b000101110101 $
1%
b000101110101 (
b010101000 )
b000101110101 *
#1730000000
0!
0%
#1735000000
1!
b000101011001 $
1%
b000101011001 (
b010101001 )
b000101011001 *
#1740000000
0!
0%
#1745000000
1!
b000100111110 $
1%
b000100111110 (
b010101010 )
b000100111110 *
#1750000000
0!
0%
#1755000000
1!
b000100100011 $
1%
b000100100011 (
b010101011 )
b000100100011 *
#1760000000
0!
0%
#1765000000
1!
b000100001010 $
1%
b000100001010 (
b010101100 )
b000100001010 *
#1770000000
0!
0%
#1775000000
1!
b000011110010 $
1%
b000011110010 (
b010101101 )
b000011110010 *
#1780000000
0!
0%
#1785000000
1!
b000011011011 $
1%
b000011011011 (
b010101110 )
b000011011011 *
#1790000000
0!
0%
#1795000000
1!
b000011000101 $
1%
b000011000101 (
b010101111 )
b000011000101 *
#1800000000
0!
0%
#1805000000
1!
b000010110000 $
1%
b000010110000 (
b010110000 )
b000010110000 *
#1810000000
0!
0%
#1815000000
1!
b000010011100 $
1%
b000010011100 (
b010110001 )
b000010011100 *
#1820000000
0!
0%
#1825000000
1!
b000010001001 $
1%
b000010001001 (
b010110010 )
b000010001001 *
#1830000000
0!
0%
#1835000000
1!
b000001111000 $
1%
b000001111000 (
b010110011 )
b000001111000 *
#1840000000
0!
0%
#1845000000
1!
b000001100111 $
1%
b000001100111 (
b010110100 )
b000001100111 *
#1850000000
0!
0%
#1855000000
1!
b000001011000 $
1%
b000001011000 (
b010110101 )
b000001011000 *
#1860000000
0!
0%
#1865000000
1!
b000001001010 $
1%
b000001001010 (
b010110110 )
b000001001010 *
#1870000000
0!
0%
#1875000000
1!
b000000111101 $
1%
b000000111101 (
b010110111 )
b000000111101 *
#1880000000
0!
0%
#1885000000
1!
b000000110010 $
1%
b000000110010 (
b010111000 )
b000000110010 *
#1890000000
0!
0%
#1895000000
1!
b000000100111 $
1%
b000000100111 (
b010111001 )
b000000100111 *
#1900000000
0!
0%
#1905000000
1!
b000000011110 $
1%
b000000011110 (
b010111010 )
b000000011110 *
#1910000000
0!
0%
#1915000000
1!
b000000010110 $
1%
b000000010110 (
b010111011 )
b000000010110 *
#1920000000
0!
0%
#1925000000
1!
b000000001111 $
1%
b000000001111 (
b010111100 )
b000000001111 *
#1930000000
0!
0%
#1935000000
1!
b000000001010 $
1%
b000000001010 (
b010111101 )
b000000001010 *
#1940000000
0!
0%
#1945000000
1!
b000000000110 $
1%
b000000000110 (
b010111110 )
b000000000110 *
#1950000000
0!
0%
#1955000000
1!
b000000000010 $
1%
b000000000010 (
b010111111 )
b000000000010 *
#1960000000
0!
0%
#1965000000
1!
b000000000001 $
1%
b000000000001 (
b011000000 )
b000000000001 *
#1970000000
0!
0%
#1975000000
1!
b000000000000 $
1%
b000000000000 (
b011000001 )
b000000000000 *
#1980000000
0!
0%
#1985000000
1!
b000000000001 $
1%
b000000000001 (
b011000010 )
b000000000001 *
#1990000000
0!
0%
#1995000000
1!
b000000000010 $
1%
b000000000010 (
b011000011 )
b000000000010 *
#2000000000
0!
0%
#2005000000
1!
b000000000110 $
1%
b000000000110 (
b011000100 )
b000000000110 *
#2010000000
0!
0%
#2015000000
1!
b000000001010 $
1%
b000000001010 (
b011000101 )
b000000001010 *
#2020000000
0!
0%
#2025000000
1!
b000000001111 $
1%
b000000001111 (
b011000110 )
b000000001111 *
#2030000000
0!
0%
#2035000000
1!
b000000010110 $
1%
b000000010110 (
b011000111 )
b000000010110 *
#2040000000
0!
0%
#2045000000
1!
b000000011110 $
1%
b000000011110 (
b011001000 )
b000000011110 *
#2050000000
0!
0%
#2055000000
1!
b000000100111 $
1%
b000000100111 (
b011001001 )
b000000100111 *
#2060000000
0!
0%
#2065000000
1!
b000000110010 $
1%
b000000110010 (
b011001010 )
b000000110010 *
#2070000000
0!
0%
#2075000000
1!
b000000111101 $
1%
b000000111101 (
b011001011 )
b000000111101 *
#2080000000
0!
0%
#2085000000
1!
b000001001010 $
1%
b000001001010 (
b011001100 )
b000001001010 *
#2090000000
0!
0%
#2095000000
1!
b000001011000 $
1%
b000001011000 (
b011001101 )
b000001011000 *
#2100000000
0!
0%
#2105000000
1!
b000001100111 $
1%
b000001100111 (
b011001110 )
b000001100111 *
#2110000000
0!
0%
#2115000000
1!
b000001111000 $
1%
b000001111000 (
b011001111 )
b000001111000 *
#2120000000
0!
0%
#2125000000
1!
b000010001001 $
1%
b000010001001 (
b011010000 )
b000010001001 *
#2130000000
0!
0%
#2135000000
1!
b000010011100 $
1%
b000010011100 (
b011010001 )
b000010011100 *
#2140000000
0!
0%
#2145000000
1!
b000010110000 $
1%
b000010110000 (
b011010010 )
b000010110000 *
#2150000000
0!
0%
#2155000000
1!
b000011000101 $
1%
b000011000101 (
b011010011 )
b000011000101 *
#2160000000
0!
0%
#2165000000
1!
b000011011011 $
1%
b000011011011 (
b011010100 )
b000011011011 *
#2170000000
0!
0%
#2175000000
1!
b000011110010 $
1%
b000011110010 (
b011010101 )
b000011110010 *
#2180000000
0!
0%
#2185000000
1!
b000100001010 $
1%
b000100001010 (
b011010110 )
b000100001010 *
#2190000000
0!
0%
#2195000000
1!
b000100100011 $
1%
b000100100011 (
b011010111 )
b000100100011 *
#2200000000
0!
0%
#2205000000
1!
b000100111110 $
1%
b000100111110 (
b011011000 )
b000100111110 *
#2210000000
0!
0%
